{"search-results": {"opensearch:totalResults": "44", "opensearch:startIndex": "0", "opensearch:itemsPerPage": "44", "opensearch:Query": {"@role": "request", "@searchTerms": "issn(17506352)", "@startPage": "0"}, "link": [{"@_fa": "true", "@ref": "self", "@href": "https://api.elsevier.com/content/search/scopus?start=0&count=200&query=issn%2817506352%29&date=2011&apiKey=ad4e12568b69167a2d25213b52923901&insttoken=0363e8707601cf3e7f27138d2b25f9e4", "@type": "application/json"}, {"@_fa": "true", "@ref": "first", "@href": "https://api.elsevier.com/content/search/scopus?start=0&count=200&query=issn%2817506352%29&date=2011&apiKey=ad4e12568b69167a2d25213b52923901&insttoken=0363e8707601cf3e7f27138d2b25f9e4", "@type": "application/json"}], "entry": [{"@_fa": "true", "link": [{"@_fa": "true", "@ref": "self", "@href": "https://api.elsevier.com/content/abstract/scopus_id/84855953116"}, {"@_fa": "true", "@ref": "author-affiliation", "@href": "https://api.elsevier.com/content/abstract/scopus_id/84855953116?field=author,affiliation"}, {"@_fa": "true", "@ref": "scopus", "@href": "https://www.scopus.com/inward/record.uri?partnerID=HzOxMe3b&scp=84855953116&origin=inward"}, {"@_fa": "true", "@ref": "scopus-citedby", "@href": "https://www.scopus.com/inward/citedby.uri?partnerID=HzOxMe3b&scp=84855953116&origin=inward"}], "prism:url": "https://api.elsevier.com/content/abstract/scopus_id/84855953116", "dc:identifier": "SCOPUS_ID:84855953116", "eid": "2-s2.0-84855953116", "dc:title": "Rich digital media as a tool in post-conflict truth and reconciliation", "dc:creator": "Best M.L.", "prism:publicationName": "Media, War and Conflict", "prism:issn": "17506352", "prism:eIssn": "17506360", "prism:volume": "4", "prism:issueIdentifier": "3", "prism:pageRange": "231-249", "prism:coverDate": "2011-12-01", "prism:coverDisplayDate": "December 2011", "prism:doi": "10.1177/1750635211420628", "citedby-count": "12", "affiliation": [{"@_fa": "true", "affilname": "Georgia Institute of Technology", "affiliation-city": "Atlanta", "affiliation-country": "United States"}], "prism:aggregationType": "Journal", "subtype": "ar", "subtypeDescription": "Article", "source-id": "16300154767", "openaccess": "0", "openaccessFlag": false}, {"@_fa": "true", "link": [{"@_fa": "true", "@ref": "self", "@href": "https://api.elsevier.com/content/abstract/scopus_id/84855951573"}, {"@_fa": "true", "@ref": "author-affiliation", "@href": "https://api.elsevier.com/content/abstract/scopus_id/84855951573?field=author,affiliation"}, {"@_fa": "true", "@ref": "scopus", "@href": "https://www.scopus.com/inward/record.uri?partnerID=HzOxMe3b&scp=84855951573&origin=inward"}, {"@_fa": "true", "@ref": "scopus-citedby", "@href": "https://www.scopus.com/inward/citedby.uri?partnerID=HzOxMe3b&scp=84855951573&origin=inward"}], "prism:url": "https://api.elsevier.com/content/abstract/scopus_id/84855951573", "dc:identifier": "SCOPUS_ID:84855951573", "eid": "2-s2.0-84855951573", "dc:title": "Combat cuties: Photographs of Israeli women soldiers in the press since the 2006 Lebanon War", "dc:creator": "Berger E.", "prism:publicationName": "Media, War and Conflict", "prism:issn": "17506352", "prism:eIssn": "17506360", "prism:volume": "4", "prism:issueIdentifier": "3", "prism:pageRange": "269-286", "prism:coverDate": "2011-12-01", "prism:coverDisplayDate": "December 2011", "prism:doi": "10.1177/1750635211420630", "citedby-count": "7", "affiliation": [{"@_fa": "true", "affilname": "College of Management Academic Studies Israel", "affiliation-city": "Rishon Letsiyon", "affiliation-country": "Israel"}], "prism:aggregationType": "Journal", "subtype": "re", "subtypeDescription": "Review", "source-id": "16300154767", "openaccess": "0", "openaccessFlag": false}, {"@_fa": "true", "link": [{"@_fa": "true", "@ref": "self", "@href": "https://api.elsevier.com/content/abstract/scopus_id/84855937153"}, {"@_fa": "true", "@ref": "author-affiliation", "@href": "https://api.elsevier.com/content/abstract/scopus_id/84855937153?field=author,affiliation"}, {"@_fa": "true", "@ref": "scopus", "@href": "https://www.scopus.com/inward/record.uri?partnerID=HzOxMe3b&scp=84855937153&origin=inward"}, {"@_fa": "true", "@ref": "scopus-citedby", "@href": "https://www.scopus.com/inward/citedby.uri?partnerID=HzOxMe3b&scp=84855937153&origin=inward"}], "prism:url": "https://api.elsevier.com/content/abstract/scopus_id/84855937153", "dc:identifier": "SCOPUS_ID:84855937153", "eid": "2-s2.0-84855937153", "dc:title": "Editors' note", "dc:creator": "Hoskins A.", "prism:publicationName": "Media, War and Conflict", "prism:issn": "17506352", "prism:eIssn": "17506360", "prism:volume": "4", "prism:issueIdentifier": "3", "prism:pageRange": "211-212", "prism:coverDate": "2011-12-01", "prism:coverDisplayDate": "December 2011", "prism:doi": "10.1177/1750635211420625", "citedby-count": "0", "affiliation": [{"@_fa": "true", "affilname": "University of Glasgow", "affiliation-city": "Glasgow", "affiliation-country": "United Kingdom"}], "prism:aggregationType": "Journal", "subtype": "ed", "subtypeDescription": "Editorial", "source-id": "16300154767", "openaccess": "0", "openaccessFlag": false}, {"@_fa": "true", "link": [{"@_fa": "true", "@ref": "self", "@href": "https://api.elsevier.com/content/abstract/scopus_id/84855936827"}, {"@_fa": "true", "@ref": "author-affiliation", "@href": "https://api.elsevier.com/content/abstract/scopus_id/84855936827?field=author,affiliation"}, {"@_fa": "true", "@ref": "scopus", "@href": "https://www.scopus.com/inward/record.uri?partnerID=HzOxMe3b&scp=84855936827&origin=inward"}, {"@_fa": "true", "@ref": "scopus-citedby", "@href": "https://www.scopus.com/inward/citedby.uri?partnerID=HzOxMe3b&scp=84855936827&origin=inward"}], "prism:url": "https://api.elsevier.com/content/abstract/scopus_id/84855936827", "dc:identifier": "SCOPUS_ID:84855936827", "eid": "2-s2.0-84855936827", "dc:title": "Newspaper coverage of post political election violence in Africa: An assessment of the Kenyan example", "dc:creator": "Onyebadi U.", "prism:publicationName": "Media, War and Conflict", "prism:issn": "17506352", "prism:eIssn": "17506360", "prism:volume": "4", "prism:issueIdentifier": "3", "prism:pageRange": "215-230", "prism:coverDate": "2011-12-01", "prism:coverDisplayDate": "December 2011", "prism:doi": "10.1177/1750635211420768", "citedby-count": "12", "affiliation": [{"@_fa": "true", "affilname": "Southern Illinois University at Carbondale", "affiliation-city": "Carbondale", "affiliation-country": "United States"}], "prism:aggregationType": "Journal", "subtype": "ar", "subtypeDescription": "Article", "source-id": "16300154767", "openaccess": "0", "openaccessFlag": false}, {"@_fa": "true", "link": [{"@_fa": "true", "@ref": "self", "@href": "https://api.elsevier.com/content/abstract/scopus_id/84855935387"}, {"@_fa": "true", "@ref": "author-affiliation", "@href": "https://api.elsevier.com/content/abstract/scopus_id/84855935387?field=author,affiliation"}, {"@_fa": "true", "@ref": "scopus", "@href": "https://www.scopus.com/inward/record.uri?partnerID=HzOxMe3b&scp=84855935387&origin=inward"}, {"@_fa": "true", "@ref": "scopus-citedby", "@href": "https://www.scopus.com/inward/citedby.uri?partnerID=HzOxMe3b&scp=84855935387&origin=inward"}], "prism:url": "https://api.elsevier.com/content/abstract/scopus_id/84855935387", "dc:identifier": "SCOPUS_ID:84855935387", "eid": "2-s2.0-84855935387", "dc:title": "Proactive crisis communication? News coverage of international conflicts in German print and broadcasting media", "dc:creator": "Zillich A.", "prism:publicationName": "Media, War and Conflict", "prism:issn": "17506352", "prism:eIssn": "17506360", "prism:volume": "4", "prism:issueIdentifier": "3", "prism:pageRange": "251-267", "prism:coverDate": "2011-12-01", "prism:coverDisplayDate": "December 2011", "prism:doi": "10.1177/1750635211420629", "citedby-count": "7", "affiliation": [{"@_fa": "true", "affilname": "Friedrich Schiller Universit\u00e4t Jena", "affiliation-city": "Jena", "affiliation-country": "Germany"}], "prism:aggregationType": "Journal", "subtype": "re", "subtypeDescription": "Review", "source-id": "16300154767", "openaccess": "0", "openaccessFlag": false}, {"@_fa": "true", "link": [{"@_fa": "true", "@ref": "self", "@href": "https://api.elsevier.com/content/abstract/scopus_id/84855923291"}, {"@_fa": "true", "@ref": "author-affiliation", "@href": "https://api.elsevier.com/content/abstract/scopus_id/84855923291?field=author,affiliation"}, {"@_fa": "true", "@ref": "scopus", "@href": "https://www.scopus.com/inward/record.uri?partnerID=HzOxMe3b&scp=84855923291&origin=inward"}, {"@_fa": "true", "@ref": "scopus-citedby", "@href": "https://www.scopus.com/inward/citedby.uri?partnerID=HzOxMe3b&scp=84855923291&origin=inward"}], "prism:url": "https://api.elsevier.com/content/abstract/scopus_id/84855923291", "dc:identifier": "SCOPUS_ID:84855923291", "eid": "2-s2.0-84855923291", "dc:title": "The circle of terror: Strategic localizations of global media terror meta-discourses in the US, India and Scotland", "dc:creator": "Roy S.", "prism:publicationName": "Media, War and Conflict", "prism:issn": "17506352", "prism:eIssn": "17506360", "prism:volume": "4", "prism:issueIdentifier": "3", "prism:pageRange": "287-301", "prism:coverDate": "2011-12-01", "prism:coverDisplayDate": "December 2011", "prism:doi": "10.1177/1750635211420631", "citedby-count": "13", "affiliation": [{"@_fa": "true", "affilname": "Stephen F. Austin State University", "affiliation-city": "Nacogdoches", "affiliation-country": "United States"}], "prism:aggregationType": "Journal", "subtype": "re", "subtypeDescription": "Review", "source-id": "16300154767", "openaccess": "0", "openaccessFlag": false}, {"@_fa": "true", "link": [{"@_fa": "true", "@ref": "self", "@href": "https://api.elsevier.com/content/abstract/scopus_id/79961118317"}, {"@_fa": "true", "@ref": "author-affiliation", "@href": "https://api.elsevier.com/content/abstract/scopus_id/79961118317?field=author,affiliation"}, {"@_fa": "true", "@ref": "scopus", "@href": "https://www.scopus.com/inward/record.uri?partnerID=HzOxMe3b&scp=79961118317&origin=inward"}, {"@_fa": "true", "@ref": "scopus-citedby", "@href": "https://www.scopus.com/inward/citedby.uri?partnerID=HzOxMe3b&scp=79961118317&origin=inward"}], "prism:url": "https://api.elsevier.com/content/abstract/scopus_id/79961118317", "dc:identifier": "SCOPUS_ID:79961118317", "eid": "2-s2.0-79961118317", "dc:title": "Twenty-first-century drug warriors: The press, privateers and the for-profit waging of the war on drugs", "dc:creator": "Schack T.", "prism:publicationName": "Media, War and Conflict", "prism:issn": "17506352", "prism:eIssn": "17506360", "prism:volume": "4", "prism:issueIdentifier": "2", "prism:pageRange": "142-161", "prism:coverDate": "2011-08-01", "prism:coverDisplayDate": "August 2011", "prism:doi": "10.1177/1750635211406013", "citedby-count": "6", "affiliation": [{"@_fa": "true", "affilname": "Ithaca College", "affiliation-city": "Ithaca", "affiliation-country": "United States"}], "prism:aggregationType": "Journal", "subtype": "ar", "subtypeDescription": "Article", "source-id": "16300154767", "openaccess": "0", "openaccessFlag": false}, {"@_fa": "true", "link": [{"@_fa": "true", "@ref": "self", "@href": "https://api.elsevier.com/content/abstract/scopus_id/79961078102"}, {"@_fa": "true", "@ref": "author-affiliation", "@href": "https://api.elsevier.com/content/abstract/scopus_id/79961078102?field=author,affiliation"}, {"@_fa": "true", "@ref": "scopus", "@href": "https://www.scopus.com/inward/record.uri?partnerID=HzOxMe3b&scp=79961078102&origin=inward"}, {"@_fa": "true", "@ref": "scopus-citedby", "@href": "https://www.scopus.com/inward/citedby.uri?partnerID=HzOxMe3b&scp=79961078102&origin=inward"}], "prism:url": "https://api.elsevier.com/content/abstract/scopus_id/79961078102", "dc:identifier": "SCOPUS_ID:79961078102", "eid": "2-s2.0-79961078102", "dc:title": "Bottlenecks in the coverage of the Israeli-Palestinian conflict: The coverage of the first and second intifada in the Flemish press", "dc:creator": "Deprez A.", "prism:publicationName": "Media, War and Conflict", "prism:issn": "17506352", "prism:eIssn": "17506360", "prism:volume": "4", "prism:issueIdentifier": "2", "prism:pageRange": "185-202", "prism:coverDate": "2011-08-01", "prism:coverDisplayDate": "August 2011", "prism:doi": "10.1177/1750635211406612", "citedby-count": "3", "affiliation": [{"@_fa": "true", "affilname": "Universiteit Gent", "affiliation-city": "Ghent", "affiliation-country": "Belgium"}], "prism:aggregationType": "Journal", "subtype": "ar", "subtypeDescription": "Article", "source-id": "16300154767", "openaccess": "0", "openaccessFlag": false}, {"@_fa": "true", "link": [{"@_fa": "true", "@ref": "self", "@href": "https://api.elsevier.com/content/abstract/scopus_id/79961070829"}, {"@_fa": "true", "@ref": "author-affiliation", "@href": "https://api.elsevier.com/content/abstract/scopus_id/79961070829?field=author,affiliation"}, {"@_fa": "true", "@ref": "scopus", "@href": "https://www.scopus.com/inward/record.uri?partnerID=HzOxMe3b&scp=79961070829&origin=inward"}, {"@_fa": "true", "@ref": "scopus-citedby", "@href": "https://www.scopus.com/inward/citedby.uri?partnerID=HzOxMe3b&scp=79961070829&origin=inward"}], "prism:url": "https://api.elsevier.com/content/abstract/scopus_id/79961070829", "dc:identifier": "SCOPUS_ID:79961070829", "eid": "2-s2.0-79961070829", "dc:title": "Editors' note", "dc:creator": "Hoskins A.", "prism:publicationName": "Media, War and Conflict", "prism:issn": "17506352", "prism:eIssn": "17506360", "prism:volume": "4", "prism:issueIdentifier": "2", "prism:pageRange": "107-108", "prism:coverDate": "2011-08-01", "prism:coverDisplayDate": "August 2011", "prism:doi": "10.1177/1750635211401992", "citedby-count": "1", "affiliation": [{"@_fa": "true", "affilname": "University of Nottingham", "affiliation-city": "Nottingham", "affiliation-country": "United Kingdom"}], "prism:aggregationType": "Journal", "subtype": "ed", "subtypeDescription": "Editorial", "source-id": "16300154767", "openaccess": "0", "openaccessFlag": false}, {"@_fa": "true", "link": [{"@_fa": "true", "@ref": "self", "@href": "https://api.elsevier.com/content/abstract/scopus_id/79961055136"}, {"@_fa": "true", "@ref": "author-affiliation", "@href": "https://api.elsevier.com/content/abstract/scopus_id/79961055136?field=author,affiliation"}, {"@_fa": "true", "@ref": "scopus", "@href": "https://www.scopus.com/inward/record.uri?partnerID=HzOxMe3b&scp=79961055136&origin=inward"}, {"@_fa": "true", "@ref": "scopus-citedby", "@href": "https://www.scopus.com/inward/citedby.uri?partnerID=HzOxMe3b&scp=79961055136&origin=inward"}], "prism:url": "https://api.elsevier.com/content/abstract/scopus_id/79961055136", "dc:identifier": "SCOPUS_ID:79961055136", "eid": "2-s2.0-79961055136", "dc:title": "Mediating sovereignty: A comparative latent semantic analysis of US newspapers and conflicts in Kosovo and South Ossetia", "dc:creator": "Dittmer J.", "prism:publicationName": "Media, War and Conflict", "prism:issn": "17506352", "prism:eIssn": "17506360", "prism:volume": "4", "prism:issueIdentifier": "2", "prism:pageRange": "124-141", "prism:coverDate": "2011-08-01", "prism:coverDisplayDate": "August 2011", "prism:doi": "10.1177/1750635211406014", "citedby-count": "7", "affiliation": [{"@_fa": "true", "affilname": "University College London", "affiliation-city": "London", "affiliation-country": "United Kingdom"}], "prism:aggregationType": "Journal", "subtype": "ar", "subtypeDescription": "Article", "source-id": "16300154767", "openaccess": "0", "openaccessFlag": false}, {"@_fa": "true", "link": [{"@_fa": "true", "@ref": "self", "@href": "https://api.elsevier.com/content/abstract/scopus_id/79961052745"}, {"@_fa": "true", "@ref": "author-affiliation", "@href": "https://api.elsevier.com/content/abstract/scopus_id/79961052745?field=author,affiliation"}, {"@_fa": "true", "@ref": "scopus", "@href": "https://www.scopus.com/inward/record.uri?partnerID=HzOxMe3b&scp=79961052745&origin=inward"}, {"@_fa": "true", "@ref": "scopus-citedby", "@href": "https://www.scopus.com/inward/citedby.uri?partnerID=HzOxMe3b&scp=79961052745&origin=inward"}], "prism:url": "https://api.elsevier.com/content/abstract/scopus_id/79961052745", "dc:identifier": "SCOPUS_ID:79961052745", "eid": "2-s2.0-79961052745", "dc:title": "Press coverage of the UK military budget: 1987 to 2009", "dc:creator": "Lewis J.", "prism:publicationName": "Media, War and Conflict", "prism:issn": "17506352", "prism:eIssn": "17506360", "prism:volume": "4", "prism:issueIdentifier": "2", "prism:pageRange": "162-184", "prism:coverDate": "2011-08-01", "prism:coverDisplayDate": "August 2011", "prism:doi": "10.1177/1750635211406012", "citedby-count": "1", "affiliation": [{"@_fa": "true", "affilname": "College of Arts, Humanities and Social Sciences", "affiliation-city": "Cardiff", "affiliation-country": "United Kingdom"}], "prism:aggregationType": "Journal", "subtype": "re", "subtypeDescription": "Review", "source-id": "16300154767", "openaccess": "0", "openaccessFlag": false}, {"@_fa": "true", "link": [{"@_fa": "true", "@ref": "self", "@href": "https://api.elsevier.com/content/abstract/scopus_id/79961040285"}, {"@_fa": "true", "@ref": "author-affiliation", "@href": "https://api.elsevier.com/content/abstract/scopus_id/79961040285?field=author,affiliation"}, {"@_fa": "true", "@ref": "scopus", "@href": "https://www.scopus.com/inward/record.uri?partnerID=HzOxMe3b&scp=79961040285&origin=inward"}, {"@_fa": "true", "@ref": "scopus-citedby", "@href": "https://www.scopus.com/inward/citedby.uri?partnerID=HzOxMe3b&scp=79961040285&origin=inward"}], "prism:url": "https://api.elsevier.com/content/abstract/scopus_id/79961040285", "dc:identifier": "SCOPUS_ID:79961040285", "eid": "2-s2.0-79961040285", "dc:title": "Deflecting the CNN effect: Public opinion polling and Livingstonian outcomes", "dc:creator": "Kogen L.", "prism:publicationName": "Media, War and Conflict", "prism:issn": "17506352", "prism:eIssn": "17506360", "prism:volume": "4", "prism:issueIdentifier": "2", "prism:pageRange": "109-123", "prism:coverDate": "2011-08-01", "prism:coverDisplayDate": "August 2011", "prism:doi": "10.1177/1750635211406051", "citedby-count": "4", "affiliation": [{"@_fa": "true", "affilname": "University of Pennsylvania Annenberg School for Communications", "affiliation-city": "Philadelphia", "affiliation-country": "United States"}], "prism:aggregationType": "Journal", "subtype": "ar", "subtypeDescription": "Article", "source-id": "16300154767", "openaccess": "0", "openaccessFlag": false}, {"@_fa": "true", "link": [{"@_fa": "true", "@ref": "self", "@href": "https://api.elsevier.com/content/abstract/scopus_id/84916607515"}, {"@_fa": "true", "@ref": "author-affiliation", "@href": "https://api.elsevier.com/content/abstract/scopus_id/84916607515?field=author,affiliation"}, {"@_fa": "true", "@ref": "scopus", "@href": "https://www.scopus.com/inward/record.uri?partnerID=HzOxMe3b&scp=84916607515&origin=inward"}, {"@_fa": "true", "@ref": "scopus-citedby", "@href": "https://www.scopus.com/inward/citedby.uri?partnerID=HzOxMe3b&scp=84916607515&origin=inward"}], "prism:url": "https://api.elsevier.com/content/abstract/scopus_id/84916607515", "dc:identifier": "SCOPUS_ID:84916607515", "eid": "2-s2.0-84916607515", "dc:title": "Lemierre's syndrome misdiagnosed as swine flu", "dc:creator": "Rashid A.", "prism:publicationName": "Media, War and Conflict", "prism:issn": "17506352", "prism:eIssn": "17506360", "prism:volume": "12", "prism:issueIdentifier": "2", "prism:pageRange": "155-157", "prism:coverDate": "2011-04-09", "prism:coverDisplayDate": "9 April 2011", "prism:doi": "10.1177/175114371101200217", "citedby-count": "0", "affiliation": [{"@_fa": "true", "affilname": "Milton Keynes General Hospital", "affiliation-city": "Milton Keynes", "affiliation-country": "United Kingdom"}, {"@_fa": "true", "affilname": "John Radcliffe Hospital", "affiliation-city": "Oxford", "affiliation-country": "United Kingdom"}], "prism:aggregationType": "Journal", "subtype": "ar", "subtypeDescription": "Article", "source-id": "16300154767", "openaccess": "0", "openaccessFlag": false}, {"@_fa": "true", "link": [{"@_fa": "true", "@ref": "self", "@href": "https://api.elsevier.com/content/abstract/scopus_id/79955037677"}, {"@_fa": "true", "@ref": "author-affiliation", "@href": "https://api.elsevier.com/content/abstract/scopus_id/79955037677?field=author,affiliation"}, {"@_fa": "true", "@ref": "scopus", "@href": "https://www.scopus.com/inward/record.uri?partnerID=HzOxMe3b&scp=79955037677&origin=inward"}, {"@_fa": "true", "@ref": "scopus-citedby", "@href": "https://www.scopus.com/inward/citedby.uri?partnerID=HzOxMe3b&scp=79955037677&origin=inward"}], "prism:url": "https://api.elsevier.com/content/abstract/scopus_id/79955037677", "dc:identifier": "SCOPUS_ID:79955037677", "eid": "2-s2.0-79955037677", "dc:title": "Japanese foreign disaster assistance: The ad hoc period in international politics and the illusion of a CNN effect", "dc:creator": "Van Belle D.", "prism:publicationName": "Media, War and Conflict", "prism:issn": "17506352", "prism:eIssn": "17506360", "prism:volume": "4", "prism:issueIdentifier": "1", "prism:pageRange": "83-95", "prism:coverDate": "2011-04-01", "prism:coverDisplayDate": "April 2011", "prism:doi": "10.1177/1750635210396125", "citedby-count": "3", "affiliation": [{"@_fa": "true", "affilname": "Victoria University of Wellington", "affiliation-city": "Wellington", "affiliation-country": "New Zealand"}], "prism:aggregationType": "Journal", "subtype": "ar", "subtypeDescription": "Article", "source-id": "16300154767", "openaccess": "0", "openaccessFlag": false}, {"@_fa": "true", "link": [{"@_fa": "true", "@ref": "self", "@href": "https://api.elsevier.com/content/abstract/scopus_id/79955035078"}, {"@_fa": "true", "@ref": "author-affiliation", "@href": "https://api.elsevier.com/content/abstract/scopus_id/79955035078?field=author,affiliation"}, {"@_fa": "true", "@ref": "scopus", "@href": "https://www.scopus.com/inward/record.uri?partnerID=HzOxMe3b&scp=79955035078&origin=inward"}, {"@_fa": "true", "@ref": "scopus-citedby", "@href": "https://www.scopus.com/inward/citedby.uri?partnerID=HzOxMe3b&scp=79955035078&origin=inward"}], "prism:url": "https://api.elsevier.com/content/abstract/scopus_id/79955035078", "dc:identifier": "SCOPUS_ID:79955035078", "eid": "2-s2.0-79955035078", "dc:title": "Media and foreign policy in central and eastern Europe post 9/11: In from the cold?", "dc:creator": "Balabanova E.", "prism:publicationName": "Media, War and Conflict", "prism:issn": "17506352", "prism:eIssn": "17506360", "prism:volume": "4", "prism:issueIdentifier": "1", "prism:pageRange": "69-82", "prism:coverDate": "2011-04-01", "prism:coverDisplayDate": "April 2011", "prism:doi": "10.1177/1750635210396124", "citedby-count": "3", "affiliation": [{"@_fa": "true", "affilname": "University of Liverpool", "affiliation-city": "Liverpool", "affiliation-country": "United Kingdom"}], "prism:aggregationType": "Journal", "subtype": "ar", "subtypeDescription": "Article", "source-id": "16300154767", "openaccess": "0", "openaccessFlag": false}, {"@_fa": "true", "link": [{"@_fa": "true", "@ref": "self", "@href": "https://api.elsevier.com/content/abstract/scopus_id/79955034104"}, {"@_fa": "true", "@ref": "author-affiliation", "@href": "https://api.elsevier.com/content/abstract/scopus_id/79955034104?field=author,affiliation"}, {"@_fa": "true", "@ref": "scopus", "@href": "https://www.scopus.com/inward/record.uri?partnerID=HzOxMe3b&scp=79955034104&origin=inward"}, {"@_fa": "true", "@ref": "scopus-citedby", "@href": "https://www.scopus.com/inward/citedby.uri?partnerID=HzOxMe3b&scp=79955034104&origin=inward"}], "prism:url": "https://api.elsevier.com/content/abstract/scopus_id/79955034104", "dc:identifier": "SCOPUS_ID:79955034104", "eid": "2-s2.0-79955034104", "dc:title": "The CNN effect reconsidered (again): Problematizing ICT and global governance in the CNN effect research agenda", "dc:creator": "Livingston S.", "prism:publicationName": "Media, War and Conflict", "prism:issn": "17506352", "prism:eIssn": "17506360", "prism:volume": "4", "prism:issueIdentifier": "1", "prism:pageRange": "20-36", "prism:coverDate": "2011-04-01", "prism:coverDisplayDate": "April 2011", "prism:doi": "10.1177/1750635210396127", "citedby-count": "16", "affiliation": [{"@_fa": "true", "affilname": "Elliott School of International Affairs", "affiliation-city": "Washington, D.C.", "affiliation-country": "United States"}], "prism:aggregationType": "Journal", "subtype": "ar", "subtypeDescription": "Article", "source-id": "16300154767", "openaccess": "0", "openaccessFlag": false}, {"@_fa": "true", "link": [{"@_fa": "true", "@ref": "self", "@href": "https://api.elsevier.com/content/abstract/scopus_id/79955023107"}, {"@_fa": "true", "@ref": "author-affiliation", "@href": "https://api.elsevier.com/content/abstract/scopus_id/79955023107?field=author,affiliation"}, {"@_fa": "true", "@ref": "scopus", "@href": "https://www.scopus.com/inward/record.uri?partnerID=HzOxMe3b&scp=79955023107&origin=inward"}, {"@_fa": "true", "@ref": "scopus-citedby", "@href": "https://www.scopus.com/inward/citedby.uri?partnerID=HzOxMe3b&scp=79955023107&origin=inward"}], "prism:url": "https://api.elsevier.com/content/abstract/scopus_id/79955023107", "dc:identifier": "SCOPUS_ID:79955023107", "eid": "2-s2.0-79955023107", "dc:title": "Did the global war on terror end the CNN effect?", "dc:creator": "Bahador B.", "prism:publicationName": "Media, War and Conflict", "prism:issn": "17506352", "prism:eIssn": "17506360", "prism:volume": "4", "prism:issueIdentifier": "1", "prism:pageRange": "37-54", "prism:coverDate": "2011-04-01", "prism:coverDisplayDate": "April 2011", "prism:doi": "10.1177/1750635210396123", "citedby-count": "4", "affiliation": [{"@_fa": "true", "affilname": "University of Canterbury", "affiliation-city": "Christchurch", "affiliation-country": "New Zealand"}], "prism:aggregationType": "Journal", "subtype": "ar", "subtypeDescription": "Article", "source-id": "16300154767", "openaccess": "0", "openaccessFlag": false}, {"@_fa": "true", "link": [{"@_fa": "true", "@ref": "self", "@href": "https://api.elsevier.com/content/abstract/scopus_id/79955022483"}, {"@_fa": "true", "@ref": "author-affiliation", "@href": "https://api.elsevier.com/content/abstract/scopus_id/79955022483?field=author,affiliation"}, {"@_fa": "true", "@ref": "scopus", "@href": "https://www.scopus.com/inward/record.uri?partnerID=HzOxMe3b&scp=79955022483&origin=inward"}, {"@_fa": "true", "@ref": "scopus-citedby", "@href": "https://www.scopus.com/inward/citedby.uri?partnerID=HzOxMe3b&scp=79955022483&origin=inward"}], "prism:url": "https://api.elsevier.com/content/abstract/scopus_id/79955022483", "dc:identifier": "SCOPUS_ID:79955022483", "eid": "2-s2.0-79955022483", "dc:title": "Time to move on: New media realities - New vulnerabilities of power", "dc:creator": "Gowing N.", "prism:publicationName": "Media, War and Conflict", "prism:issn": "17506352", "prism:eIssn": "17506360", "prism:volume": "4", "prism:issueIdentifier": "1", "prism:pageRange": "13-19", "prism:coverDate": "2011-04-01", "prism:coverDisplayDate": "April 2011", "prism:doi": "10.1177/1750635210397637", "citedby-count": "11", "affiliation": [{"@_fa": "true", "affilname": "British Broadcasting Corporation", "affiliation-city": "London", "affiliation-country": "United Kingdom"}], "prism:aggregationType": "Journal", "subtype": "no", "subtypeDescription": "Note", "source-id": "16300154767", "openaccess": "0", "openaccessFlag": false}, {"@_fa": "true", "link": [{"@_fa": "true", "@ref": "self", "@href": "https://api.elsevier.com/content/abstract/scopus_id/79955018198"}, {"@_fa": "true", "@ref": "author-affiliation", "@href": "https://api.elsevier.com/content/abstract/scopus_id/79955018198?field=author,affiliation"}, {"@_fa": "true", "@ref": "scopus", "@href": "https://www.scopus.com/inward/record.uri?partnerID=HzOxMe3b&scp=79955018198&origin=inward"}, {"@_fa": "true", "@ref": "scopus-citedby", "@href": "https://www.scopus.com/inward/citedby.uri?partnerID=HzOxMe3b&scp=79955018198&origin=inward"}], "prism:url": "https://api.elsevier.com/content/abstract/scopus_id/79955018198", "dc:identifier": "SCOPUS_ID:79955018198", "eid": "2-s2.0-79955018198", "dc:title": "The CNN effect reconsidered: Mapping a research agenda for the future", "dc:creator": "Robinson P.", "prism:publicationName": "Media, War and Conflict", "prism:issn": "17506352", "prism:eIssn": "17506360", "prism:volume": "4", "prism:issueIdentifier": "1", "prism:pageRange": "3-11", "prism:coverDate": "2011-04-01", "prism:coverDisplayDate": "April 2011", "prism:doi": "10.1177/1750635210397434", "citedby-count": "24", "affiliation": [{"@_fa": "true", "affilname": "The University of Manchester", "affiliation-city": "Manchester", "affiliation-country": "United Kingdom"}], "prism:aggregationType": "Journal", "subtype": "re", "subtypeDescription": "Review", "source-id": "16300154767", "openaccess": "0", "openaccessFlag": false}, {"@_fa": "true", "link": [{"@_fa": "true", "@ref": "self", "@href": "https://api.elsevier.com/content/abstract/scopus_id/79955016836"}, {"@_fa": "true", "@ref": "author-affiliation", "@href": "https://api.elsevier.com/content/abstract/scopus_id/79955016836?field=author,affiliation"}, {"@_fa": "true", "@ref": "scopus", "@href": "https://www.scopus.com/inward/record.uri?partnerID=HzOxMe3b&scp=79955016836&origin=inward"}, {"@_fa": "true", "@ref": "scopus-citedby", "@href": "https://www.scopus.com/inward/citedby.uri?partnerID=HzOxMe3b&scp=79955016836&origin=inward"}], "prism:url": "https://api.elsevier.com/content/abstract/scopus_id/79955016836", "dc:identifier": "SCOPUS_ID:79955016836", "eid": "2-s2.0-79955016836", "dc:title": "Media selectivity and the other side of the CNN effect: The consequences of not paying attention to conflict", "dc:creator": "Hawkins V.", "prism:publicationName": "Media, War and Conflict", "prism:issn": "17506352", "prism:eIssn": "17506360", "prism:volume": "4", "prism:issueIdentifier": "1", "prism:pageRange": "55-68", "prism:coverDate": "2011-04-01", "prism:coverDisplayDate": "April 2011", "prism:doi": "10.1177/1750635210396126", "citedby-count": "27", "affiliation": [{"@_fa": "true", "affilname": "Osaka University", "affiliation-city": "Suita", "affiliation-country": "Japan"}], "prism:aggregationType": "Journal", "subtype": "ar", "subtypeDescription": "Article", "source-id": "16300154767", "openaccess": "0", "openaccessFlag": false}, {"@_fa": "true", "link": [{"@_fa": "true", "@ref": "self", "@href": "https://api.elsevier.com/content/abstract/scopus_id/84992889575"}, {"@_fa": "true", "@ref": "author-affiliation", "@href": "https://api.elsevier.com/content/abstract/scopus_id/84992889575?field=author,affiliation"}, {"@_fa": "true", "@ref": "scopus", "@href": "https://www.scopus.com/inward/record.uri?partnerID=HzOxMe3b&scp=84992889575&origin=inward"}, {"@_fa": "true", "@ref": "scopus-citedby", "@href": "https://www.scopus.com/inward/citedby.uri?partnerID=HzOxMe3b&scp=84992889575&origin=inward"}], "prism:url": "https://api.elsevier.com/content/abstract/scopus_id/84992889575", "dc:identifier": "SCOPUS_ID:84992889575", "eid": "2-s2.0-84992889575", "dc:title": "Exhibition review", "dc:creator": "Goodall M.", "prism:publicationName": "Media, War &amp; Conflict", "prism:issn": "17506352", "prism:volume": "4", "prism:issueIdentifier": "1", "prism:pageRange": "102-104", "prism:coverDate": "2011-01-01", "prism:coverDisplayDate": "April 2011", "prism:doi": "10.1177/17506352110040010804", "citedby-count": "0", "affiliation": [{"@_fa": "true", "affilname": "University of Bradford", "affiliation-city": "Bradford", "affiliation-country": "United Kingdom"}], "prism:aggregationType": "Journal", "subtype": "re", "subtypeDescription": "Review", "source-id": "16300154767", "openaccess": "0", "openaccessFlag": false}, {"@_fa": "true", "link": [{"@_fa": "true", "@ref": "self", "@href": "https://api.elsevier.com/content/abstract/scopus_id/84992785032"}, {"@_fa": "true", "@ref": "author-affiliation", "@href": "https://api.elsevier.com/content/abstract/scopus_id/84992785032?field=author,affiliation"}, {"@_fa": "true", "@ref": "scopus", "@href": "https://www.scopus.com/inward/record.uri?partnerID=HzOxMe3b&scp=84992785032&origin=inward"}, {"@_fa": "true", "@ref": "scopus-citedby", "@href": "https://www.scopus.com/inward/citedby.uri?partnerID=HzOxMe3b&scp=84992785032&origin=inward"}], "prism:url": "https://api.elsevier.com/content/abstract/scopus_id/84992785032", "dc:identifier": "SCOPUS_ID:84992785032", "eid": "2-s2.0-84992785032", "dc:title": "Film review", "dc:creator": "Lieberfeld D.", "prism:publicationName": "Media, War &amp; Conflict", "prism:issn": "17506352", "prism:volume": "4", "prism:issueIdentifier": "2", "prism:pageRange": "207-208", "prism:coverDate": "2011-01-01", "prism:coverDisplayDate": "August 2011", "prism:doi": "10.1177/17506352110040020703", "citedby-count": "0", "affiliation": [{"@_fa": "true", "affilname": "Duquesne University", "affiliation-city": "Pittsburgh", "affiliation-country": "United States"}], "prism:aggregationType": "Journal", "subtype": "re", "subtypeDescription": "Review", "source-id": "16300154767", "openaccess": "0", "openaccessFlag": false}, {"@_fa": "true", "link": [{"@_fa": "true", "@ref": "self", "@href": "https://api.elsevier.com/content/abstract/scopus_id/84992782770"}, {"@_fa": "true", "@ref": "author-affiliation", "@href": "https://api.elsevier.com/content/abstract/scopus_id/84992782770?field=author,affiliation"}, {"@_fa": "true", "@ref": "scopus", "@href": "https://www.scopus.com/inward/record.uri?partnerID=HzOxMe3b&scp=84992782770&origin=inward"}, {"@_fa": "true", "@ref": "scopus-citedby", "@href": "https://www.scopus.com/inward/citedby.uri?partnerID=HzOxMe3b&scp=84992782770&origin=inward"}], "prism:url": "https://api.elsevier.com/content/abstract/scopus_id/84992782770", "dc:identifier": "SCOPUS_ID:84992782770", "eid": "2-s2.0-84992782770", "dc:title": "Tributes to Phil Taylor (1954\u20132010): The art of communication \u2013 remembering a friend and colleague", "dc:creator": "Hoskins A.", "prism:publicationName": "Media, War &amp; Conflict", "prism:issn": "17506352", "prism:eIssn": "17506360", "prism:volume": "4", "prism:issueIdentifier": "3", "prism:pageRange": "213-214", "prism:coverDate": "2011-01-01", "prism:coverDisplayDate": "December 2011", "prism:doi": "10.1177/1750635211420626", "citedby-count": "0", "affiliation": [{"@_fa": "true", "affilname": "University of Glasgow", "affiliation-city": "Glasgow", "affiliation-country": "United Kingdom"}], "prism:aggregationType": "Journal", "subtype": "ar", "subtypeDescription": "Article", "source-id": "16300154767", "openaccess": "0", "openaccessFlag": false}, {"@_fa": "true", "link": [{"@_fa": "true", "@ref": "self", "@href": "https://api.elsevier.com/content/abstract/scopus_id/84916640805"}, {"@_fa": "true", "@ref": "author-affiliation", "@href": "https://api.elsevier.com/content/abstract/scopus_id/84916640805?field=author,affiliation"}, {"@_fa": "true", "@ref": "scopus", "@href": "https://www.scopus.com/inward/record.uri?partnerID=HzOxMe3b&scp=84916640805&origin=inward"}, {"@_fa": "true", "@ref": "scopus-citedby", "@href": "https://www.scopus.com/inward/citedby.uri?partnerID=HzOxMe3b&scp=84916640805&origin=inward"}], "prism:url": "https://api.elsevier.com/content/abstract/scopus_id/84916640805", "dc:identifier": "SCOPUS_ID:84916640805", "eid": "2-s2.0-84916640805", "dc:title": "Early neuromuscular blockade in severe ARDS", "dc:creator": "Horner D.", "prism:publicationName": "Media, War and Conflict", "prism:issn": "17506352", "prism:eIssn": "17506360", "prism:volume": "12", "prism:issueIdentifier": "2", "prism:pageRange": "153-154", "prism:coverDate": "2011-01-01", "prism:coverDisplayDate": "9 April 2011", "prism:doi": "10.1177/175114371101200216", "citedby-count": "0", "affiliation": [{"@_fa": "true", "affilname": "Manchester Royal Infirmary", "affiliation-city": "Manchester", "affiliation-country": "United Kingdom"}], "prism:aggregationType": "Journal", "subtype": "re", "subtypeDescription": "Review", "source-id": "16300154767", "openaccess": "0", "openaccessFlag": false}, {"@_fa": "true", "link": [{"@_fa": "true", "@ref": "self", "@href": "https://api.elsevier.com/content/abstract/scopus_id/84916639113"}, {"@_fa": "true", "@ref": "author-affiliation", "@href": "https://api.elsevier.com/content/abstract/scopus_id/84916639113?field=author,affiliation"}, {"@_fa": "true", "@ref": "scopus", "@href": "https://www.scopus.com/inward/record.uri?partnerID=HzOxMe3b&scp=84916639113&origin=inward"}, {"@_fa": "true", "@ref": "scopus-citedby", "@href": "https://www.scopus.com/inward/citedby.uri?partnerID=HzOxMe3b&scp=84916639113&origin=inward"}], "prism:url": "https://api.elsevier.com/content/abstract/scopus_id/84916639113", "dc:identifier": "SCOPUS_ID:84916639113", "eid": "2-s2.0-84916639113", "dc:title": "Multimodal cerebral monitoring in traumatic brain injury", "dc:creator": "Vidgeon S.D.", "prism:publicationName": "Media, War and Conflict", "prism:issn": "17506352", "prism:eIssn": "17506360", "prism:volume": "12", "prism:issueIdentifier": "2", "prism:pageRange": "126-133", "prism:coverDate": "2011-01-01", "prism:coverDisplayDate": "9 April 2011", "prism:doi": "10.1177/175114371101200208", "citedby-count": "1", "affiliation": [{"@_fa": "true", "affilname": "King's College Hospital", "affiliation-city": "London", "affiliation-country": "United Kingdom"}], "prism:aggregationType": "Journal", "subtype": "re", "subtypeDescription": "Review", "source-id": "16300154767", "openaccess": "0", "openaccessFlag": false}, {"@_fa": "true", "link": [{"@_fa": "true", "@ref": "self", "@href": "https://api.elsevier.com/content/abstract/scopus_id/84916634704"}, {"@_fa": "true", "@ref": "author-affiliation", "@href": "https://api.elsevier.com/content/abstract/scopus_id/84916634704?field=author,affiliation"}, {"@_fa": "true", "@ref": "scopus", "@href": "https://www.scopus.com/inward/record.uri?partnerID=HzOxMe3b&scp=84916634704&origin=inward"}, {"@_fa": "true", "@ref": "scopus-citedby", "@href": "https://www.scopus.com/inward/citedby.uri?partnerID=HzOxMe3b&scp=84916634704&origin=inward"}], "prism:url": "https://api.elsevier.com/content/abstract/scopus_id/84916634704", "dc:identifier": "SCOPUS_ID:84916634704", "eid": "2-s2.0-84916634704", "dc:title": "Nebulised heparin is associated with fewer days of mechanical ventilation in critically ill patients", "dc:creator": "Gross J.", "prism:publicationName": "Media, War and Conflict", "prism:issn": "17506352", "prism:eIssn": "17506360", "prism:volume": "12", "prism:issueIdentifier": "2", "prism:pageRange": "151-152", "prism:coverDate": "2011-01-01", "prism:coverDisplayDate": "9 April 2011", "prism:doi": "10.1177/175114371101200215", "citedby-count": "0", "affiliation": [{"@_fa": "true", "affilname": "Faculty of Intensive Care Medicine", "affiliation-city": "London", "affiliation-country": "United Kingdom"}], "prism:aggregationType": "Journal", "subtype": "re", "subtypeDescription": "Review", "source-id": "16300154767", "openaccess": "0", "openaccessFlag": false}, {"@_fa": "true", "link": [{"@_fa": "true", "@ref": "self", "@href": "https://api.elsevier.com/content/abstract/scopus_id/84916633743"}, {"@_fa": "true", "@ref": "author-affiliation", "@href": "https://api.elsevier.com/content/abstract/scopus_id/84916633743?field=author,affiliation"}, {"@_fa": "true", "@ref": "scopus", "@href": "https://www.scopus.com/inward/record.uri?partnerID=HzOxMe3b&scp=84916633743&origin=inward"}, {"@_fa": "true", "@ref": "scopus-citedby", "@href": "https://www.scopus.com/inward/citedby.uri?partnerID=HzOxMe3b&scp=84916633743&origin=inward"}], "prism:url": "https://api.elsevier.com/content/abstract/scopus_id/84916633743", "dc:identifier": "SCOPUS_ID:84916633743", "eid": "2-s2.0-84916633743", "dc:title": "Airway management on the intensive care unit - Is it time for our own training and guidelines?", "dc:creator": "Walters J.", "prism:publicationName": "Media, War and Conflict", "prism:issn": "17506352", "prism:eIssn": "17506360", "prism:volume": "12", "prism:issueIdentifier": "2", "prism:pageRange": "163-164", "prism:coverDate": "2011-01-01", "prism:coverDisplayDate": "9 April 2011", "prism:doi": "10.1177/175114371101200221", "citedby-count": "0", "affiliation": [{"@_fa": "true", "affilname": "Bristol Royal Infirmary", "affiliation-city": "Bristol", "affiliation-country": "United Kingdom"}], "prism:aggregationType": "Journal", "subtype": "le", "subtypeDescription": "Letter", "source-id": "16300154767", "openaccess": "1", "openaccessFlag": true}, {"@_fa": "true", "link": [{"@_fa": "true", "@ref": "self", "@href": "https://api.elsevier.com/content/abstract/scopus_id/84916631470"}, {"@_fa": "true", "@ref": "author-affiliation", "@href": "https://api.elsevier.com/content/abstract/scopus_id/84916631470?field=author,affiliation"}, {"@_fa": "true", "@ref": "scopus", "@href": "https://www.scopus.com/inward/record.uri?partnerID=HzOxMe3b&scp=84916631470&origin=inward"}, {"@_fa": "true", "@ref": "scopus-citedby", "@href": "https://www.scopus.com/inward/citedby.uri?partnerID=HzOxMe3b&scp=84916631470&origin=inward"}], "prism:url": "https://api.elsevier.com/content/abstract/scopus_id/84916631470", "dc:identifier": "SCOPUS_ID:84916631470", "eid": "2-s2.0-84916631470", "dc:title": "A protocol of no sedation for critically ill patients receiving mechanical ventilation: A randomised trial", "dc:creator": "Harlow G.", "prism:publicationName": "Media, War and Conflict", "prism:issn": "17506352", "prism:eIssn": "17506360", "prism:volume": "12", "prism:issueIdentifier": "2", "prism:pageRange": "147-148", "prism:coverDate": "2011-01-01", "prism:coverDisplayDate": "9 April 2011", "prism:doi": "10.1177/175114371101200213", "citedby-count": "0", "affiliation": [{"@_fa": "true", "affilname": "Queen Elizabeth Hospital, University Hospital Birmingham NHS Foundation Trust", "affiliation-city": "Birmingham", "affiliation-country": "United Kingdom"}], "prism:aggregationType": "Journal", "subtype": "re", "subtypeDescription": "Review", "source-id": "16300154767", "openaccess": "0", "openaccessFlag": false}, {"@_fa": "true", "link": [{"@_fa": "true", "@ref": "self", "@href": "https://api.elsevier.com/content/abstract/scopus_id/84916631423"}, {"@_fa": "true", "@ref": "author-affiliation", "@href": "https://api.elsevier.com/content/abstract/scopus_id/84916631423?field=author,affiliation"}, {"@_fa": "true", "@ref": "scopus", "@href": "https://www.scopus.com/inward/record.uri?partnerID=HzOxMe3b&scp=84916631423&origin=inward"}, {"@_fa": "true", "@ref": "scopus-citedby", "@href": "https://www.scopus.com/inward/citedby.uri?partnerID=HzOxMe3b&scp=84916631423&origin=inward"}], "prism:url": "https://api.elsevier.com/content/abstract/scopus_id/84916631423", "dc:identifier": "SCOPUS_ID:84916631423", "eid": "2-s2.0-84916631423", "dc:title": "Report of the NAP4 airway project", "dc:creator": "Cook T.", "prism:publicationName": "Media, War and Conflict", "prism:issn": "17506352", "prism:eIssn": "17506360", "prism:volume": "12", "prism:issueIdentifier": "2", "prism:pageRange": "107-111", "prism:coverDate": "2011-01-01", "prism:coverDisplayDate": "9 April 2011", "prism:doi": "10.1177/175114371101200206", "citedby-count": "0", "affiliation": [{"@_fa": "true", "affilname": "Royal United Hospital, Bath", "affiliation-city": "Bath", "affiliation-country": "United Kingdom"}], "prism:aggregationType": "Journal", "subtype": "ar", "subtypeDescription": "Article", "source-id": "16300154767", "openaccess": "1", "openaccessFlag": true}, {"@_fa": "true", "link": [{"@_fa": "true", "@ref": "self", "@href": "https://api.elsevier.com/content/abstract/scopus_id/84916631236"}, {"@_fa": "true", "@ref": "author-affiliation", "@href": "https://api.elsevier.com/content/abstract/scopus_id/84916631236?field=author,affiliation"}, {"@_fa": "true", "@ref": "scopus", "@href": "https://www.scopus.com/inward/record.uri?partnerID=HzOxMe3b&scp=84916631236&origin=inward"}, {"@_fa": "true", "@ref": "scopus-citedby", "@href": "https://www.scopus.com/inward/citedby.uri?partnerID=HzOxMe3b&scp=84916631236&origin=inward"}], "prism:url": "https://api.elsevier.com/content/abstract/scopus_id/84916631236", "dc:identifier": "SCOPUS_ID:84916631236", "eid": "2-s2.0-84916631236", "dc:title": "Post-traumatic invasive mucormycosis", "dc:creator": "Marchetti A.", "prism:publicationName": "Media, War and Conflict", "prism:issn": "17506352", "prism:eIssn": "17506360", "prism:volume": "12", "prism:issueIdentifier": "2", "prism:pageRange": "143-144", "prism:coverDate": "2011-01-01", "prism:coverDisplayDate": "9 April 2011", "prism:doi": "10.1177/175114371101200211", "citedby-count": "0", "affiliation": [{"@_fa": "true", "affilname": "Royal Liverpool University Hospital", "affiliation-city": "Liverpool", "affiliation-country": "United Kingdom"}], "prism:aggregationType": "Journal", "subtype": "ar", "subtypeDescription": "Article", "source-id": "16300154767", "openaccess": "1", "openaccessFlag": true}, {"@_fa": "true", "link": [{"@_fa": "true", "@ref": "self", "@href": "https://api.elsevier.com/content/abstract/scopus_id/84916630623"}, {"@_fa": "true", "@ref": "author-affiliation", "@href": "https://api.elsevier.com/content/abstract/scopus_id/84916630623?field=author,affiliation"}, {"@_fa": "true", "@ref": "scopus", "@href": "https://www.scopus.com/inward/record.uri?partnerID=HzOxMe3b&scp=84916630623&origin=inward"}, {"@_fa": "true", "@ref": "scopus-citedby", "@href": "https://www.scopus.com/inward/citedby.uri?partnerID=HzOxMe3b&scp=84916630623&origin=inward"}], "prism:url": "https://api.elsevier.com/content/abstract/scopus_id/84916630623", "dc:identifier": "SCOPUS_ID:84916630623", "eid": "2-s2.0-84916630623", "dc:title": "Review of current practice of blood and component transfusion: Critical issues for the critically ill patient", "dc:creator": "Padmakumar A.D.", "prism:publicationName": "Media, War and Conflict", "prism:issn": "17506352", "prism:eIssn": "17506360", "prism:volume": "12", "prism:issueIdentifier": "2", "prism:pageRange": "134-139", "prism:coverDate": "2011-01-01", "prism:coverDisplayDate": "9 April 2011", "prism:doi": "10.1177/175114371101200209", "citedby-count": "0", "affiliation": [{"@_fa": "true", "affilname": "St James's University Hospital", "affiliation-city": "Leeds", "affiliation-country": "United Kingdom"}], "prism:aggregationType": "Journal", "subtype": "re", "subtypeDescription": "Review", "source-id": "16300154767", "openaccess": "0", "openaccessFlag": false}, {"@_fa": "true", "link": [{"@_fa": "true", "@ref": "self", "@href": "https://api.elsevier.com/content/abstract/scopus_id/84916630422"}, {"@_fa": "true", "@ref": "author-affiliation", "@href": "https://api.elsevier.com/content/abstract/scopus_id/84916630422?field=author,affiliation"}, {"@_fa": "true", "@ref": "scopus", "@href": "https://www.scopus.com/inward/record.uri?partnerID=HzOxMe3b&scp=84916630422&origin=inward"}, {"@_fa": "true", "@ref": "scopus-citedby", "@href": "https://www.scopus.com/inward/citedby.uri?partnerID=HzOxMe3b&scp=84916630422&origin=inward"}], "prism:url": "https://api.elsevier.com/content/abstract/scopus_id/84916630422", "dc:identifier": "SCOPUS_ID:84916630422", "eid": "2-s2.0-84916630422", "dc:title": "Intensive care nursing in britain: Getting the dose right", "dc:creator": "Woodcock T.", "prism:publicationName": "Media, War and Conflict", "prism:issn": "17506352", "prism:eIssn": "17506360", "prism:volume": "12", "prism:issueIdentifier": "2", "prism:pageRange": "163", "prism:coverDate": "2011-01-01", "prism:coverDisplayDate": "9 April 2011", "prism:doi": "10.1177/175114371101200220", "citedby-count": "0", "affiliation": [{"@_fa": "true", "affilname": "Southampton General Hospital", "affiliation-city": "Southampton", "affiliation-country": "United Kingdom"}], "prism:aggregationType": "Journal", "subtype": "le", "subtypeDescription": "Letter", "source-id": "16300154767", "openaccess": "0", "openaccessFlag": false}, {"@_fa": "true", "link": [{"@_fa": "true", "@ref": "self", "@href": "https://api.elsevier.com/content/abstract/scopus_id/84916628445"}, {"@_fa": "true", "@ref": "author-affiliation", "@href": "https://api.elsevier.com/content/abstract/scopus_id/84916628445?field=author,affiliation"}, {"@_fa": "true", "@ref": "scopus", "@href": "https://www.scopus.com/inward/record.uri?partnerID=HzOxMe3b&scp=84916628445&origin=inward"}, {"@_fa": "true", "@ref": "scopus-citedby", "@href": "https://www.scopus.com/inward/citedby.uri?partnerID=HzOxMe3b&scp=84916628445&origin=inward"}], "prism:url": "https://api.elsevier.com/content/abstract/scopus_id/84916628445", "dc:identifier": "SCOPUS_ID:84916628445", "eid": "2-s2.0-84916628445", "dc:title": "Mobilising oedema in the oedematous critically ill patient with ARDS: Do we seek natriuresis not diuresis?", "dc:creator": "Morris C.", "prism:publicationName": "Media, War and Conflict", "prism:issn": "17506352", "prism:eIssn": "17506360", "prism:volume": "12", "prism:issueIdentifier": "2", "prism:pageRange": "92-97", "prism:coverDate": "2011-01-01", "prism:coverDisplayDate": "9 April 2011", "prism:doi": "10.1177/175114371101200204", "citedby-count": "0", "affiliation": [{"@_fa": "true", "affilname": "Royal Derby Hospital", "affiliation-city": "Derby", "affiliation-country": "United Kingdom"}], "prism:aggregationType": "Journal", "subtype": "ar", "subtypeDescription": "Article", "source-id": "16300154767", "openaccess": "1", "openaccessFlag": true}, {"@_fa": "true", "link": [{"@_fa": "true", "@ref": "self", "@href": "https://api.elsevier.com/content/abstract/scopus_id/84916625102"}, {"@_fa": "true", "@ref": "author-affiliation", "@href": "https://api.elsevier.com/content/abstract/scopus_id/84916625102?field=author,affiliation"}, {"@_fa": "true", "@ref": "scopus", "@href": "https://www.scopus.com/inward/record.uri?partnerID=HzOxMe3b&scp=84916625102&origin=inward"}, {"@_fa": "true", "@ref": "scopus-citedby", "@href": "https://www.scopus.com/inward/citedby.uri?partnerID=HzOxMe3b&scp=84916625102&origin=inward"}], "prism:url": "https://api.elsevier.com/content/abstract/scopus_id/84916625102", "dc:identifier": "SCOPUS_ID:84916625102", "eid": "2-s2.0-84916625102", "dc:title": "The fluid facts of fraud", "dc:creator": "Soni N.", "prism:publicationName": "Media, War and Conflict", "prism:issn": "17506352", "prism:eIssn": "17506360", "prism:volume": "12", "prism:issueIdentifier": "2", "prism:pageRange": "90-91", "prism:coverDate": "2011-01-01", "prism:coverDisplayDate": "9 April 2011", "prism:doi": "10.1177/175114371101200203", "citedby-count": "0", "affiliation": [{"@_fa": "true", "affilname": "Chelsea and Westminster Hospital", "affiliation-city": "London", "affiliation-country": "United Kingdom"}], "prism:aggregationType": "Journal", "subtype": "ed", "subtypeDescription": "Editorial", "source-id": "16300154767", "openaccess": "0", "openaccessFlag": false}, {"@_fa": "true", "link": [{"@_fa": "true", "@ref": "self", "@href": "https://api.elsevier.com/content/abstract/scopus_id/84916607102"}, {"@_fa": "true", "@ref": "author-affiliation", "@href": "https://api.elsevier.com/content/abstract/scopus_id/84916607102?field=author,affiliation"}, {"@_fa": "true", "@ref": "scopus", "@href": "https://www.scopus.com/inward/record.uri?partnerID=HzOxMe3b&scp=84916607102&origin=inward"}, {"@_fa": "true", "@ref": "scopus-citedby", "@href": "https://www.scopus.com/inward/citedby.uri?partnerID=HzOxMe3b&scp=84916607102&origin=inward"}], "prism:url": "https://api.elsevier.com/content/abstract/scopus_id/84916607102", "dc:identifier": "SCOPUS_ID:84916607102", "eid": "2-s2.0-84916607102", "dc:title": "End-of-life care in scottish intensive care units", "dc:creator": "Hamza S.", "prism:publicationName": "Media, War and Conflict", "prism:issn": "17506352", "prism:eIssn": "17506360", "prism:volume": "12", "prism:issueIdentifier": "2", "prism:pageRange": "164-165", "prism:coverDate": "2011-01-01", "prism:coverDisplayDate": "9 April 2011", "prism:doi": "10.1177/175114371101200222", "citedby-count": "0", "affiliation": [{"@_fa": "true", "affilname": "Western Infirmary", "affiliation-city": "Glasgow", "affiliation-country": "United Kingdom"}], "prism:aggregationType": "Journal", "subtype": "le", "subtypeDescription": "Letter", "source-id": "16300154767", "openaccess": "0", "openaccessFlag": false}, {"@_fa": "true", "link": [{"@_fa": "true", "@ref": "self", "@href": "https://api.elsevier.com/content/abstract/scopus_id/84916605713"}, {"@_fa": "true", "@ref": "author-affiliation", "@href": "https://api.elsevier.com/content/abstract/scopus_id/84916605713?field=author,affiliation"}, {"@_fa": "true", "@ref": "scopus", "@href": "https://www.scopus.com/inward/record.uri?partnerID=HzOxMe3b&scp=84916605713&origin=inward"}, {"@_fa": "true", "@ref": "scopus-citedby", "@href": "https://www.scopus.com/inward/citedby.uri?partnerID=HzOxMe3b&scp=84916605713&origin=inward"}], "prism:url": "https://api.elsevier.com/content/abstract/scopus_id/84916605713", "dc:identifier": "SCOPUS_ID:84916605713", "eid": "2-s2.0-84916605713", "dc:title": "This month in JICS", "dc:creator": "Harper J.", "prism:publicationName": "Media, War and Conflict", "prism:issn": "17506352", "prism:eIssn": "17506360", "prism:volume": "12", "prism:issueIdentifier": "2", "prism:pageRange": "86", "prism:coverDate": "2011-01-01", "prism:coverDisplayDate": "9 April 2011", "prism:doi": "10.1177/175114371101200201", "citedby-count": "0", "prism:aggregationType": "Journal", "subtype": "ed", "subtypeDescription": "Editorial", "source-id": "16300154767", "openaccess": "1", "openaccessFlag": true}, {"@_fa": "true", "link": [{"@_fa": "true", "@ref": "self", "@href": "https://api.elsevier.com/content/abstract/scopus_id/84916604299"}, {"@_fa": "true", "@ref": "author-affiliation", "@href": "https://api.elsevier.com/content/abstract/scopus_id/84916604299?field=author,affiliation"}, {"@_fa": "true", "@ref": "scopus", "@href": "https://www.scopus.com/inward/record.uri?partnerID=HzOxMe3b&scp=84916604299&origin=inward"}, {"@_fa": "true", "@ref": "scopus-citedby", "@href": "https://www.scopus.com/inward/citedby.uri?partnerID=HzOxMe3b&scp=84916604299&origin=inward"}], "prism:url": "https://api.elsevier.com/content/abstract/scopus_id/84916604299", "dc:identifier": "SCOPUS_ID:84916604299", "eid": "2-s2.0-84916604299", "dc:title": "Centralisation of specialist critical care services", "dc:creator": "Meadows C.", "prism:publicationName": "Media, War and Conflict", "prism:issn": "17506352", "prism:eIssn": "17506360", "prism:volume": "12", "prism:issueIdentifier": "2", "prism:pageRange": "87-89", "prism:coverDate": "2011-01-01", "prism:coverDisplayDate": "9 April 2011", "prism:doi": "10.1177/175114371101200202", "citedby-count": "0", "affiliation": [{"@_fa": "true", "affilname": "Royal Brompton Hospital", "affiliation-city": "London", "affiliation-country": "United Kingdom"}], "prism:aggregationType": "Journal", "subtype": "ed", "subtypeDescription": "Editorial", "source-id": "16300154767", "openaccess": "0", "openaccessFlag": false}, {"@_fa": "true", "link": [{"@_fa": "true", "@ref": "self", "@href": "https://api.elsevier.com/content/abstract/scopus_id/84916603480"}, {"@_fa": "true", "@ref": "author-affiliation", "@href": "https://api.elsevier.com/content/abstract/scopus_id/84916603480?field=author,affiliation"}, {"@_fa": "true", "@ref": "scopus", "@href": "https://www.scopus.com/inward/record.uri?partnerID=HzOxMe3b&scp=84916603480&origin=inward"}, {"@_fa": "true", "@ref": "scopus-citedby", "@href": "https://www.scopus.com/inward/citedby.uri?partnerID=HzOxMe3b&scp=84916603480&origin=inward"}], "prism:url": "https://api.elsevier.com/content/abstract/scopus_id/84916603480", "dc:identifier": "SCOPUS_ID:84916603480", "eid": "2-s2.0-84916603480", "dc:title": "Intensity of renal replacement therapy: Effects on mortality and renal recovery", "dc:creator": "Hornsby J.", "prism:publicationName": "Media, War and Conflict", "prism:issn": "17506352", "prism:eIssn": "17506360", "prism:volume": "12", "prism:issueIdentifier": "2", "prism:pageRange": "149-150", "prism:coverDate": "2011-01-01", "prism:coverDisplayDate": "9 April 2011", "prism:doi": "10.1177/175114371101200214", "citedby-count": "0", "affiliation": [{"@_fa": "true", "affilname": "Stirling Community Hospital", "affiliation-city": "Stirling", "affiliation-country": "United Kingdom"}], "prism:aggregationType": "Journal", "subtype": "re", "subtypeDescription": "Review", "source-id": "16300154767", "openaccess": "0", "openaccessFlag": false}, {"@_fa": "true", "link": [{"@_fa": "true", "@ref": "self", "@href": "https://api.elsevier.com/content/abstract/scopus_id/84916602948"}, {"@_fa": "true", "@ref": "author-affiliation", "@href": "https://api.elsevier.com/content/abstract/scopus_id/84916602948?field=author,affiliation"}, {"@_fa": "true", "@ref": "scopus", "@href": "https://www.scopus.com/inward/record.uri?partnerID=HzOxMe3b&scp=84916602948&origin=inward"}, {"@_fa": "true", "@ref": "scopus-citedby", "@href": "https://www.scopus.com/inward/citedby.uri?partnerID=HzOxMe3b&scp=84916602948&origin=inward"}], "prism:url": "https://api.elsevier.com/content/abstract/scopus_id/84916602948", "dc:identifier": "SCOPUS_ID:84916602948", "eid": "2-s2.0-84916602948", "dc:title": "The knowledge of medical students and newly qualified doctors concerning the specialty of intensive care medicine", "dc:creator": "Kelly D.", "prism:publicationName": "Media, War and Conflict", "prism:issn": "17506352", "prism:eIssn": "17506360", "prism:volume": "12", "prism:issueIdentifier": "2", "prism:pageRange": "98-106", "prism:coverDate": "2011-01-01", "prism:coverDisplayDate": "9 April 2011", "prism:doi": "10.1177/175114371101200205", "citedby-count": "0", "affiliation": [{"@_fa": "true", "affilname": "Brighton and Sussex Medical School", "affiliation-city": "Brighton", "affiliation-country": "United Kingdom"}], "prism:aggregationType": "Journal", "subtype": "ar", "subtypeDescription": "Article", "source-id": "16300154767", "openaccess": "1", "openaccessFlag": true}, {"@_fa": "true", "link": [{"@_fa": "true", "@ref": "self", "@href": "https://api.elsevier.com/content/abstract/scopus_id/84916602548"}, {"@_fa": "true", "@ref": "author-affiliation", "@href": "https://api.elsevier.com/content/abstract/scopus_id/84916602548?field=author,affiliation"}, {"@_fa": "true", "@ref": "scopus", "@href": "https://www.scopus.com/inward/record.uri?partnerID=HzOxMe3b&scp=84916602548&origin=inward"}, {"@_fa": "true", "@ref": "scopus-citedby", "@href": "https://www.scopus.com/inward/citedby.uri?partnerID=HzOxMe3b&scp=84916602548&origin=inward"}], "prism:url": "https://api.elsevier.com/content/abstract/scopus_id/84916602548", "dc:identifier": "SCOPUS_ID:84916602548", "eid": "2-s2.0-84916602548", "dc:title": "Do critical care networks make a difference? How the north west critical care networks shaped the response to the H1N1 outbreak in 2010/11", "dc:creator": "Masterson G.", "prism:publicationName": "Media, War and Conflict", "prism:issn": "17506352", "prism:eIssn": "17506360", "prism:volume": "12", "prism:issueIdentifier": "2", "prism:pageRange": "161-162", "prism:coverDate": "2011-01-01", "prism:coverDisplayDate": "9 April 2011", "prism:doi": "10.1177/175114371101200219", "citedby-count": "0", "affiliation": [{"@_fa": "true", "affilname": "Royal Liverpool University Hospital", "affiliation-city": "Liverpool", "affiliation-country": "United Kingdom"}, {"@_fa": "true", "affilname": "Medical Lead", "affiliation-city": null, "affiliation-country": "United Kingdom"}], "prism:aggregationType": "Journal", "subtype": "ar", "subtypeDescription": "Article", "source-id": "16300154767", "openaccess": "1", "openaccessFlag": true}, {"@_fa": "true", "link": [{"@_fa": "true", "@ref": "self", "@href": "https://api.elsevier.com/content/abstract/scopus_id/84916600966"}, {"@_fa": "true", "@ref": "author-affiliation", "@href": "https://api.elsevier.com/content/abstract/scopus_id/84916600966?field=author,affiliation"}, {"@_fa": "true", "@ref": "scopus", "@href": "https://www.scopus.com/inward/record.uri?partnerID=HzOxMe3b&scp=84916600966&origin=inward"}, {"@_fa": "true", "@ref": "scopus-citedby", "@href": "https://www.scopus.com/inward/citedby.uri?partnerID=HzOxMe3b&scp=84916600966&origin=inward"}], "prism:url": "https://api.elsevier.com/content/abstract/scopus_id/84916600966", "dc:identifier": "SCOPUS_ID:84916600966", "eid": "2-s2.0-84916600966", "dc:title": "The outcomes of adult patients with haematological malignancy requiring admission to the intensive care unit", "dc:creator": "McDowall K.", "prism:publicationName": "Media, War and Conflict", "prism:issn": "17506352", "prism:eIssn": "17506360", "prism:volume": "12", "prism:issueIdentifier": "2", "prism:pageRange": "112-125", "prism:coverDate": "2011-01-01", "prism:coverDisplayDate": "9 April 2011", "prism:doi": "10.1177/175114371101200207", "citedby-count": "2", "affiliation": [{"@_fa": "true", "affilname": "Southern General Hospital Glasgow", "affiliation-city": "Glasgow", "affiliation-country": "United Kingdom"}], "prism:aggregationType": "Journal", "subtype": "re", "subtypeDescription": "Review", "source-id": "16300154767", "openaccess": "1", "openaccessFlag": true}, {"@_fa": "true", "link": [{"@_fa": "true", "@ref": "self", "@href": "https://api.elsevier.com/content/abstract/scopus_id/84916597784"}, {"@_fa": "true", "@ref": "author-affiliation", "@href": "https://api.elsevier.com/content/abstract/scopus_id/84916597784?field=author,affiliation"}, {"@_fa": "true", "@ref": "scopus", "@href": "https://www.scopus.com/inward/record.uri?partnerID=HzOxMe3b&scp=84916597784&origin=inward"}, {"@_fa": "true", "@ref": "scopus-citedby", "@href": "https://www.scopus.com/inward/citedby.uri?partnerID=HzOxMe3b&scp=84916597784&origin=inward"}], "prism:url": "https://api.elsevier.com/content/abstract/scopus_id/84916597784", "dc:identifier": "SCOPUS_ID:84916597784", "eid": "2-s2.0-84916597784", "dc:title": "Chest compression-only CPR improves mortality compared to standard CPR", "dc:creator": "McIlmoyle K.", "prism:publicationName": "Media, War and Conflict", "prism:issn": "17506352", "prism:eIssn": "17506360", "prism:volume": "12", "prism:issueIdentifier": "2", "prism:pageRange": "145-146", "prism:coverDate": "2011-01-01", "prism:coverDisplayDate": "9 April 2011", "prism:doi": "10.1177/175114371101200212", "citedby-count": "0", "affiliation": [{"@_fa": "true", "affilname": "Stirling Community Hospital", "affiliation-city": "Stirling", "affiliation-country": "United Kingdom"}], "prism:aggregationType": "Journal", "subtype": "re", "subtypeDescription": "Review", "source-id": "16300154767", "openaccess": "0", "openaccessFlag": false}, {"@_fa": "true", "link": [{"@_fa": "true", "@ref": "self", "@href": "https://api.elsevier.com/content/abstract/scopus_id/84916596748"}, {"@_fa": "true", "@ref": "author-affiliation", "@href": "https://api.elsevier.com/content/abstract/scopus_id/84916596748?field=author,affiliation"}, {"@_fa": "true", "@ref": "scopus", "@href": "https://www.scopus.com/inward/record.uri?partnerID=HzOxMe3b&scp=84916596748&origin=inward"}, {"@_fa": "true", "@ref": "scopus-citedby", "@href": "https://www.scopus.com/inward/citedby.uri?partnerID=HzOxMe3b&scp=84916596748&origin=inward"}], "prism:url": "https://api.elsevier.com/content/abstract/scopus_id/84916596748", "dc:identifier": "SCOPUS_ID:84916596748", "eid": "2-s2.0-84916596748", "dc:title": "Rescue of acute refractory hypercapnia and acidosis secondary to life-threatening asthma with extracorporeal carbon dioxide removal (ECCO<inf>2</inf>R)", "dc:creator": "Lobaz S.", "prism:publicationName": "Media, War and Conflict", "prism:issn": "17506352", "prism:eIssn": "17506360", "prism:volume": "12", "prism:issueIdentifier": "2", "prism:pageRange": "140-142", "prism:coverDate": "2011-01-01", "prism:coverDisplayDate": "9 April 2011", "prism:doi": "10.1177/175114371101200210", "citedby-count": "1", "affiliation": [{"@_fa": "true", "affilname": "Royal Victoria Infirmary", "affiliation-city": "Newcastle", "affiliation-country": "United Kingdom"}], "prism:aggregationType": "Journal", "subtype": "ar", "subtypeDescription": "Article", "source-id": "16300154767", "openaccess": "0", "openaccessFlag": false}, {"@_fa": "true", "link": [{"@_fa": "true", "@ref": "self", "@href": "https://api.elsevier.com/content/abstract/scopus_id/84916596480"}, {"@_fa": "true", "@ref": "author-affiliation", "@href": "https://api.elsevier.com/content/abstract/scopus_id/84916596480?field=author,affiliation"}, {"@_fa": "true", "@ref": "scopus", "@href": "https://www.scopus.com/inward/record.uri?partnerID=HzOxMe3b&scp=84916596480&origin=inward"}, {"@_fa": "true", "@ref": "scopus-citedby", "@href": "https://www.scopus.com/inward/citedby.uri?partnerID=HzOxMe3b&scp=84916596480&origin=inward"}], "prism:url": "https://api.elsevier.com/content/abstract/scopus_id/84916596480", "dc:identifier": "SCOPUS_ID:84916596480", "eid": "2-s2.0-84916596480", "dc:title": "A respiratory centre and network model for the management of severe hypoxaemic respiratory failure", "dc:creator": "Parry-Jones J.", "prism:publicationName": "Media, War and Conflict", "prism:issn": "17506352", "prism:eIssn": "17506360", "prism:volume": "12", "prism:issueIdentifier": "2", "prism:pageRange": "158-160", "prism:coverDate": "2011-01-01", "prism:coverDisplayDate": "9 April 2011", "prism:doi": "10.1177/175114371101200218", "citedby-count": "0", "affiliation": [{"@_fa": "true", "affilname": "Royal Gwent Hospital", "affiliation-city": "Newport", "affiliation-country": "United Kingdom"}], "prism:aggregationType": "Journal", "subtype": "ar", "subtypeDescription": "Article", "source-id": "16300154767", "openaccess": "0", "openaccessFlag": false}]}}